pyPCG/__init__.py
pyPCG/features.py
pyPCG/io.py
pyPCG/lr_hsmm.py
pyPCG/preprocessing.py
pyPCG/segment.py
pyPCG/sqi.py
pyPCG/stats.py
pypcg_toolbox-0.1b5.dist-info/licenses/LICENSE
pypcg_toolbox-0.1b5.dist-info/METADATA
pypcg_toolbox-0.1b5.dist-info/WHEEL
pypcg_toolbox-0.1b5.dist-info/top_level.txt
pypcg_toolbox-0.1b5.dist-info/RECORD
