Metadata-Version: 2.4
Name: pyPCG_toolbox
Version: 0.1b5
Summary: A PCG processing toolbox
Home-page: https://github.com/mulkr/pyPCG-toolbox/
Author: Kristóf Müller, Janka Hatvani, Miklós Koller, Márton Áron Goda
Author-email: muller.kristof@itk.ppke.hu, goda.marton.aron@itk.ppke.hu
Maintainer-email: Kristóf Müller <muller.kristof@itk.ppke.hu>
License-Expression: GPL-3.0-only
Project-URL: Homepage, https://github.com/mulkr/pyPCG-toolbox/
Project-URL: Documentation, https://pypcg-toolbox.readthedocs.io/en/latest/
Project-URL: Repository, https://github.com/mulkr/pyPCG-toolbox.git
Project-URL: Issues, https://github.com/mulkr/pyPCG-toolbox/issues
Classifier: Development Status :: 4 - Beta
Classifier: Programming Language :: Python :: 3.10
Classifier: Operating System :: OS Independent
Classifier: Topic :: Scientific/Engineering
Requires-Python: >=3.10
License-File: LICENSE
Requires-Dist: scikit-learn>=1.1.3
Requires-Dist: scipy>=1.9.3
Requires-Dist: PyWavelets>=1.5.0
Requires-Dist: pandas>=2.0.0
Requires-Dist: matplotlib>=3.6.2
Requires-Dist: numpy>=1.25.2
Requires-Dist: emd>=0.6.2
Requires-Dist: nolds>=0.5.2
Requires-Dist: tqdm>=4.64.1
Requires-Dist: pyQt5>=5.15.7
Dynamic: author-email
Dynamic: home-page
Dynamic: license-file
Dynamic: requires-python
